<?xml version="1.0" encoding="UTF-8"?>
<objects serializationModel="Studio.02.03.00">
	<object class="AudioFile" id="{4ccf5708-27dc-423b-9c6a-c5439147ad7b}">
		<property name="assetPath">
			<value>wind-magic.wav</value>
		</property>
		<property name="frequencyInKHz">
			<value>48</value>
		</property>
		<property name="channelCount">
			<value>2</value>
		</property>
		<property name="length">
			<value>1.6070625000000001</value>
		</property>
		<relationship name="masterAssetFolder">
			<destination>{1f14b0de-9299-4197-a08b-53c6ce5acc80}</destination>
		</relationship>
	</object>
</objects>
